cdk_lambda_subminute/__init__.py
cdk_lambda_subminute/py.typed
cdk_lambda_subminute/_jsii/__init__.py
cdk_lambda_subminute/_jsii/cdk-lambda-subminute@2.0.671.jsii.tgz
cdk_lambda_subminute-2.0.671.dist-info/LICENSE
cdk_lambda_subminute-2.0.671.dist-info/METADATA
cdk_lambda_subminute-2.0.671.dist-info/WHEEL
cdk_lambda_subminute-2.0.671.dist-info/top_level.txt
cdk_lambda_subminute-2.0.671.dist-info/RECORD
